[
  {
    "arkpassive": "빛의 기사",
    "grade": "유물",
    "title": "종언의 기사",
    "details": {
      "10": "종언의 빛의 피해량이 4.0% 증가한다.",
      "14": "빛의 기사 사용 시 '운명'이 발동한다.",
      "17" : "종언의 빛의 피해량이 8.0% 증가한다.",
      "18": "종언의 빛의 피해량이 0.25% 증가한다.",
      "19": "종언의 빛의 피해량이 0.25% 증가한다.",
      "20": "종언의 빛의 피해량이 0.25% 증가한다."
    }
  },
  {
    "arkpassive": "빛의 기사",
    "grade": "고대",
    "title": "종언의 기사",
    "details": {
      "10": "종언의 빛의 피해량이 4.0% 증가한다.",
      "14": "빛의 기사 사용 시 '운명'이 발동한다.",
      "17" : "종언의 빛의 피해량이 10.0% 증가한다.",
      "18": "종언의 빛의 피해량이 0.25% 증가한다.",
      "19": "종언의 빛의 피해량이 0.25% 증가한다.",
      "20": "종언의 빛의 피해량이 0.25% 증가한다."
    }
  },
  {
    "arkpassive": "빛의 기사",
    "grade": "유물",
    "title": "빛의 안식",
    "details": {
      "10": "안식의 비, 안식의 재의 피해량이 5.0% 증가한다.",
      "14": "빛의 기사 사용 시 '운명'이 발동한다.",
      "17" : "성휘 스킬의 피해량이 12.0% 증가한다.",
      "18": "성휘 스킬의 피해량이 0.3% 증가한다.",
      "19": "성휘 스킬의 피해량이 0.3% 증가한다.",
      "20": "성휘 스킬의 피해량이 0.3% 증가한다."
    }
  },
  {
    "arkpassive": "빛의 기사",
    "grade": "고대",
    "title": "빛의 안식",
    "details": {
      "10": "안식의 비, 안식의 재의 피해량이 5.0% 증가한다.",
      "14": "빛의 기사 사용 시 '운명'이 발동한다.",
      "17" : "성휘 스킬의 피해량이 15.0% 증가한다.",
      "18": "성휘 스킬의 피해량이 0.3% 증가한다.",
      "19": "성휘 스킬의 피해량이 0.3% 증가한다.",
      "20": "성휘 스킬의 피해량이 0.3% 증가한다."
    }
  },
  {
    "arkpassive": "빛의 기사",
    "grade": "유물",
    "title": "눈부신 정의",
    "details": {
      "10": "단죄의 성흔 피해량이 40.0% 증가한다.",
      "14": "단죄의 성흔 사용 시 '운명' 이 발동한다.",
      "17" : "정의 스킬의 피해량이 20.0% 증가한다.",
      "18": "정의 스킬의 피해량이 0.45% 증가한다.",
      "19": "정의 스킬의 피해량이 0.45% 증가한다.",
      "20": "정의 스킬의 피해량이 0.45% 증가한다."
    }
  },
  {
    "arkpassive": "빛의 기사",
    "grade": "고대",
    "title": "눈부신 정의",
    "details": {
      "10": "단죄의 성흔 피해량이 40.0% 증가한다.",
      "14": "단죄의 성흔 사용 시 '운명' 이 발동한다.",
      "17" : "정의 스킬의 피해량이 25.0% 증가한다.",
      "18": "정의 스킬의 피해량이 0.45% 증가한다.",
      "19": "정의 스킬의 피해량이 0.45% 증가한다.",
      "20": "정의 스킬의 피해량이 0.45% 증가한다."
    }
  }
]